{"id":17,
"prev":"0x000877ebcc1e5847a31cc3287e08d7fdde611badc8fae66164d0575cdb4d5fdd2954658c049a62277577e8bc5792e3899889747a8588c7fafc1ab21ba9368c93",
"transactions":[{"recipient":"0x170","sender":"0x0","time":"0x1676878709","ammount":"0x0"},
{"recipient":"0x171","sender":"0x0","time":"0x1676878709","ammount":"0x0"},
{"recipient":"0x172","sender":"0x0","time":"0x1676878709","ammount":"0x0"},
{"recipient":"0x173","sender":"0x0","time":"0x1676878709","ammount":"0x0"},
{"recipient":"0x174","sender":"0x0","time":"0x1676878709","ammount":"0x0"},
{"recipient":"0x175","sender":"0x0","time":"0x1676878709","ammount":"0x0"},
{"recipient":"0x176","sender":"0x0","time":"0x1676878709","ammount":"0x0"},
{"recipient":"0x177","sender":"0x0","time":"0x1676878709","ammount":"0x0"},
{"recipient":"0x178","sender":"0x0","time":"0x1676878709","ammount":"0x0"},
{"recipient":"0x179","sender":"0x0","time":"0x1676878709","ammount":"0x0"}],
"salt":"6825"}
