{"id":36,
"prev":"0x00021e4d123e04ec407a806148184c1d7ab8829ff7e61fea6c446187a83ac93a3b2b3181052ce7b676154f2927409997026e03be9c321c3f7db30b8342843a95",
"transactions":[{"recipient":"0x360","sender":"0x0","time":"0x1676878712","ammount":"0x0"},
{"recipient":"0x361","sender":"0x0","time":"0x1676878712","ammount":"0x0"},
{"recipient":"0x362","sender":"0x0","time":"0x1676878712","ammount":"0x0"},
{"recipient":"0x363","sender":"0x0","time":"0x1676878712","ammount":"0x0"},
{"recipient":"0x364","sender":"0x0","time":"0x1676878712","ammount":"0x0"},
{"recipient":"0x365","sender":"0x0","time":"0x1676878712","ammount":"0x0"},
{"recipient":"0x366","sender":"0x0","time":"0x1676878712","ammount":"0x0"},
{"recipient":"0x367","sender":"0x0","time":"0x1676878712","ammount":"0x0"},
{"recipient":"0x368","sender":"0x0","time":"0x1676878712","ammount":"0x0"},
{"recipient":"0x369","sender":"0x0","time":"0x1676878712","ammount":"0x0"}],
"salt":"2961"}
